rylr/__init__.py
rylr-1.0.3.dist-info/METADATA
rylr-1.0.3.dist-info/WHEEL
rylr-1.0.3.dist-info/top_level.txt
rylr-1.0.3.dist-info/RECORD
