Metadata-Version: 2.4
Name: rylr
Version: 1.0.3
Summary: Python library for RYLR LoRa transceivers to simplifies communication with RYLR modules using Python
Author-email: Michael Jalloh <michaeljalloh19@gmail.com>
Maintainer-email: Michael Jalloh <michaeljalloh19@gmail.com>
License-Expression: MIT
Project-URL: issues, https://github.com/Michael-Jalloh/RYLR/issues
Project-URL: source, https://github.com/Michael-Jalloh/RYLR
Project-URL: Home-page, https://github.com/Michael-Jalloh/RYLR
Keywords: RYLR,serial,link,communication,RYLR896,RYLR406
Classifier: Development Status :: 4 - Beta
Classifier: Intended Audience :: Developers
Classifier: Topic :: Software Development :: Build Tools
Classifier: Programming Language :: Python :: 3.7
Classifier: Programming Language :: Python :: 3.8
Classifier: Programming Language :: Python :: 3.9
Classifier: Programming Language :: Python :: 3.10
Classifier: Programming Language :: Python :: 3.11
Classifier: Programming Language :: Python :: 3.12
Classifier: Programming Language :: Python :: 3.13
Requires-Python: >=3.7
Requires-Dist: pyserial>=3.5
